ziplineio/__init__.py
ziplineio/app.py
ziplineio/cache.py
ziplineio/dependency_injector.py
ziplineio/exception.py
ziplineio/handler.py
ziplineio/middleware.py
ziplineio/models.py
ziplineio/process_pool.py
ziplineio/request.py
ziplineio/request_context.py
ziplineio/response.py
ziplineio/router.py
ziplineio/service.py
ziplineio/settings.py
ziplineio/static.py
ziplineio/utils.py
ziplineio/html/jinja.py
ziplineio/validation/__init__.py
ziplineio/validation/body.py
ziplineio/validation/index.py
ziplineio/validation/query.py
ziplineio-0.1.16.dist-info/LICENSE
ziplineio-0.1.16.dist-info/METADATA
ziplineio-0.1.16.dist-info/WHEEL
ziplineio-0.1.16.dist-info/top_level.txt
ziplineio-0.1.16.dist-info/RECORD
