Metadata-Version: 2.1
Name: ziplineio
Version: 0.1.16
Summary: The funnest ASGI Web Framework
Author-email: Cam Sima <cjsima@gmail.com>
Project-URL: Homepage, https://github.com/CameronSima/ZipLine
Project-URL: Issues, https://github.com/CameronSima/ZipLine/issues
Classifier: Programming Language :: Python :: 3
Classifier: License :: OSI Approved :: MIT License
Classifier: Operating System :: OS Independent
Requires-Python: >=3.10
License-File: LICENSE
